whois.py
whois_rdap-0.0.12.dist-info/LICENSE
whois_rdap-0.0.12.dist-info/METADATA
whois_rdap-0.0.12.dist-info/WHEEL
whois_rdap-0.0.12.dist-info/top_level.txt
whois_rdap-0.0.12.dist-info/RECORD
