Metadata-Version: 2.1
Name: whois-rdap
Version: 0.0.12
Summary: A small library for using the WHOIS (arin.net) RDAP protocol for whois lookups
Home-page: https://github.com/ejohnfel/whois
Author: Eric Johnfelt
Author-email: ejohnfel@hotmail.com
License: UNKNOWN
Project-URL: Bug Tracker, https://github.com/ejohnfel/whois/issues
Platform: UNKNOWN
Classifier: Programming Language :: Python :: 3
Classifier: License :: OSI Approved :: MIT License
Classifier: Operating System :: OS Independent
Requires-Python: >=3.0
License-File: LICENSE
Requires-Dist: py-helper-mod
